setup.cfg
setup.py
edx_grades_api.egg-info/PKG-INFO
edx_grades_api.egg-info/SOURCES.txt
edx_grades_api.egg-info/dependency_links.txt
edx_grades_api.egg-info/pbr.json
edx_grades_api.egg-info/top_level.txt
grades_api/__init__.py
grades_api/errors.py
grades_api/urls.py
grades_api/v1/__init__.py
grades_api/v1/api.py
grades_api/v1/urls.py
grades_api/v1/views.py