Metadata-Version: 1.1
Name: edx-grades-api
Version: 1.0.1
Summary: Grades REST Api for Open edX
Home-page: https://github.com/IONISx/edx-grades-api
Author: IONISx
Author-email: UNKNOWN
License: AGPL
Platform: UNKNOWN
Classifier: Development Status :: 3 - Alpha
Classifier: Environment :: Web Environment
Classifier: Intended Audience :: Developers
Classifier: License :: OSI Approved :: GNU Affero General Public License v3
Classifier: Operating System :: OS Independent
Classifier: Programming Language :: Python
Classifier: Framework :: Django
